django_auth_essentials/__init__.py
django_auth_essentials/admin.py
django_auth_essentials/apps.py
django_auth_essentials/configs.py
django_auth_essentials/email.py
django_auth_essentials/forms.py
django_auth_essentials/middleware.py
django_auth_essentials/models.py
django_auth_essentials/tests.py
django_auth_essentials/urls.py
django_auth_essentials/views.py
django_auth_essentials/templates/accounts/base.html
django_auth_essentials/templates/accounts/login.html
django_auth_essentials/templates/accounts/logout.html
django_auth_essentials/templates/accounts/navbar.html
django_auth_essentials/templates/accounts/password_change.html
django_auth_essentials/templates/accounts/password_change_done.html
django_auth_essentials/templates/accounts/password_reset.html
django_auth_essentials/templates/accounts/password_reset_complete.html
django_auth_essentials/templates/accounts/password_reset_confirm.html
django_auth_essentials/templates/accounts/password_reset_done.html
django_auth_essentials/templates/accounts/profile.html
django_auth_essentials/templates/accounts/registration.html
django_auth_essentials/templates/accounts/resend_verification.html
django_auth_essentials/templates/accounts/verify.html
django_auth_essentials/templates/email/verify_email.html
django_auth_essentials-1.0.dist-info/LICENSE
django_auth_essentials-1.0.dist-info/METADATA
django_auth_essentials-1.0.dist-info/WHEEL
django_auth_essentials-1.0.dist-info/top_level.txt
django_auth_essentials-1.0.dist-info/RECORD
