Metadata-Version: 2.1
Name: django-auth-essentials
Version: 1.0
Summary: A Django app that provides authentication, password change, password reset and account verification functionalities.
Home-page: https://github.com/mah-di
Author: Iqbal Mahdi
Author-email: mahdiiqbal37@gmail.com
License: MIT
Keywords: django,authentication,email verification,account verification,auth
Platform: UNKNOWN
Classifier: Environment :: Web Environment
Classifier: Framework :: Django
Classifier: Framework :: Django :: 3.2
Classifier: Intended Audience :: Developers
Classifier: License :: OSI Approved :: MIT License
Classifier: Operating System :: OS Independent
Classifier: Programming Language :: Python
Classifier: Programming Language :: Python :: 3
Classifier: Programming Language :: Python :: 3 :: Only
Classifier: Programming Language :: Python :: 3.6
Classifier: Programming Language :: Python :: 3.7
Classifier: Programming Language :: Python :: 3.8
Classifier: Topic :: Internet :: WWW/HTTP
Classifier: Topic :: Internet :: WWW/HTTP :: Dynamic Content
Classifier: Topic :: Software Development :: Libraries :: Python Modules
Requires-Python: >=3
License-File: LICENSE
Requires-Dist: Django (>=3.0)
